<wpml-config>
    <admin-texts>
		<key name="imic_options">
            <key name="upload-repeatable-bg-image"/>
            <key name="full-screen-bg-image"/>
            <key name="header_image"/>
            <key name="logo_upload"/>
            <key name="retina_logo_upload"/>
            <key name="custom_admin_login_logo"/>
            <key name="custom_favicon"/>
            <key name="iphone_icon"/>
            <key name="iphone_icon_retina"/>
            <key name="ipad_icon"/>
            <key name="ipad_icon_retina"/>
            <key name="podcast_itunes_cover_image"/>
            <key name="site_width"/>
            <key name="content_min_height"/>
            <key name="header_area_height"/>
            <key name="social-facebook"/>
            <key name="social-twitter"/>
            <key name="social-pinterest"/>
            <key name="social-googleplus"/>
            <key name="social-youtube"/>
            <key name="social-instagram"/>
            <key name="social-vimeo"/>
            <key name="site-rss"/>
            <key name="logo_alt_text"/>
            <key name="retina_logo_width"/>
            <key name="retina_logo_height"/>
            <key name="mobile_menu_text"/>
            <key name="facebook_share_alt"/>
            <key name="twitter_share_alt"/>
            <key name="google_share_alt"/>
            <key name="tumblr_share_alt"/>
            <key name="pinterest_share_alt"/>
            <key name="reddit_share_alt"/>
            <key name="linkedin_share_alt"/>
            <key name="email_share_alt"/>
            <key name="vk_share_alt"/>
            <key name="podcast_title"/>
            <key name="podcast_description"/>
            <key name="podcast_website_url"/>
            <key name="podcast_language"/>
            <key name="podcast_copyright"/>
            <key name="podcast_webmaster_name"/>
            <key name="podcast_webmaster_email"/>
            <key name="podcast_itunes_author"/>
            <key name="podcast_itunes_subtitle"/>
            <key name="podcast_itunes_summary"/>
            <key name="podcast_itunes_owner_name"/>
            <key name="podcast_itunes_owner_email"/>
            <key name="podcast_itunes_top_category"/>
            <key name="podcast_itunes_sub_category"/>
            <key name="podcast_itunes_feed_url"/>
            <key name="calendar_event_limit"/>
            <key name="calendar_month_name"/>
            <key name="calendar_month_name_short"/>
            <key name="calendar_day_name"/>
            <key name="calendar_day_name_short"/>
            <key name="calendar_today"/>
            <key name="calendar_month"/>
            <key name="calendar_week"/>
            <key name="calendar_day"/>
            <key name="google_feed_key"/>
            <key name="google_feed_id"/>
            <key name="staff_read_more_text"/>
            <key name="header3_textarea"/>
            <key name="footer_copyright_text"/>
            <key name="podcast_itunes_summary"/>
            <key name="calendar_month_name"/>
            <key name="calendar_month_name_short"/>
            <key name="calendar_day_name"/>
            <key name="calendar_day_name_short"/>
            <key name="content_wide_width"/>
            <key name="header_wide_width"/>
            <key name="slider_behind_header"/>
            <key name="footer_wide_width"/>
            <key name="share_icon"/>
            <key name="share_post_types"/>
            <key name="event_feeds"/>
            <key name="sticky_link_color"/>
            <key name="h4_sticky_link_color"/>
            <key name="mainmenu_link_color"/>
            <key name="main_dropdown_link_color"/>
            <key name="topmenu_link_color"/>
            <key name="top_dropdown_link_color"/>
            <key name="top_footer_link_color"/>
            <key name="bottom_footer_link_color"/>
            <key name="footer_social_link_colo"/>
        </key>
    </admin-texts>
</wpml-config>